LICENSE
README.md
customtex/__init__.py
customtex/files_text.py
customtex/load_presets.py
customtex/main.py
customtex/parser.py
customtex/presets/hypersetups.json
customtex/presets/languages.json
customtex/presets/macros.json
customtex/presets/sectionstyles.json
customtex/presets/templates.json
customtex/presets/theoremstyles.json
customtex/presets/titlestyles.json
customtex-0.1.2.dist-info/LICENSE
customtex-0.1.2.dist-info/WHEEL
customtex-0.1.2.dist-info/entry_points.txt
customtex-0.1.2.dist-info/METADATA
customtex-0.1.2.dist-info/RECORD
