Metadata-Version: 2.1
Name: customtex
Version: 0.1.2
Summary: A CLI utility for setting up LaTeX projects
Home-page: https://github.com/mariovagomarzal/customtex
License: MIT
Author: Mario Vago Marzal
Author-email: mariovagomarzal@gmail.com
Requires-Python: >=3.10,<4.0
Classifier: License :: OSI Approved :: MIT License
Classifier: Programming Language :: Python :: 3
Classifier: Programming Language :: Python :: 3.10
Classifier: Programming Language :: Python :: 3.11
Requires-Dist: string-color (>=1.2.3,<2.0.0)
Project-URL: Repository, https://github.com/mariovagomarzal/customtex
